rag_knowledge_preparation/__init__.py
rag_knowledge_preparation/codebase_processing/__init__.py
rag_knowledge_preparation/codebase_processing/analysis/CodeAnalyzer.py
rag_knowledge_preparation/codebase_processing/analysis/CodeSummarizer.py
rag_knowledge_preparation/codebase_processing/analysis/DependencyAnalyzer.py
rag_knowledge_preparation/codebase_processing/analysis/__init__.py
rag_knowledge_preparation/codebase_processing/core/CodebaseConfig.py
rag_knowledge_preparation/codebase_processing/core/CodebaseConverter.py
rag_knowledge_preparation/codebase_processing/core/__init__.py
rag_knowledge_preparation/codebase_processing/export/CodebaseExporter.py
rag_knowledge_preparation/codebase_processing/export/__init__.py
rag_knowledge_preparation/codebase_processing/utils/CodebaseConstants.py
rag_knowledge_preparation/codebase_processing/utils/FileUtils.py
rag_knowledge_preparation/codebase_processing/utils/__init__.py
rag_knowledge_preparation/document_processing/DocumentConverter.py
rag_knowledge_preparation/document_processing/DocumentProcessingConfig.py
rag_knowledge_preparation/document_processing/__init__.py
rag_knowledge_preparation/utils/CustomExceptions.py
rag_knowledge_preparation/utils/__init__.py
rag_knowledge_preparation-1.0.0.dist-info/licenses/LICENSE
rag_knowledge_preparation-1.0.0.dist-info/METADATA
rag_knowledge_preparation-1.0.0.dist-info/WHEEL
rag_knowledge_preparation-1.0.0.dist-info/top_level.txt
rag_knowledge_preparation-1.0.0.dist-info/zip-safe
rag_knowledge_preparation-1.0.0.dist-info/RECORD
