Metadata-Version: 2.4
Name: rag_knowledge_preparation
Version: 1.0.0
Summary: RAG Knowledge Preparation in Python
Home-page: https://bitbucket.org/entinco/eic-aimodelknowledge-utils/src/master/lib-ragknowledgepreparation-python
Author: Enterprise Innovation Consulting LLC
Author-email: seroukhov@entinco.com
License: Commercial
Platform: any
Classifier: Intended Audience :: Developers
Classifier: License :: Other/Proprietary License
Classifier: Operating System :: OS Independent
Classifier: Programming Language :: Python
Classifier: Programming Language :: Python :: 3.12
Classifier: Programming Language :: Python :: 3.12
Classifier: Programming Language :: Python :: 3.12
Classifier: Programming Language :: Python :: 3.12
Classifier: Topic :: Software Development :: Libraries :: Python Modules
License-File: LICENSE
Requires-Dist: pytest
Requires-Dist: requests<3.0.0,>=2.27.1
Requires-Dist: urllib3<2.0.0,>=1.26.8
Requires-Dist: docling>=1.3.0
Requires-Dist: tiktoken>=0.5.0
Requires-Dist: pathspec>=0.11.0
Requires-Dist: tree-sitter>=0.20.0
Requires-Dist: tree-sitter-python>=0.20.0
Requires-Dist: tree-sitter-javascript>=0.20.0
Requires-Dist: tree-sitter-typescript>=0.20.0
Requires-Dist: pygments>=2.15.0
Requires-Dist: pydantic>=2.0.0
Requires-Dist: chardet>=5.0.0
Requires-Dist: google-generativeai>=0.3.0
Requires-Dist: pip-services4-commons>=0.0.0
Requires-Dist: pip-services4-components>=0.0.0
Requires-Dist: pip-services4-config>=0.0.0
Requires-Dist: pip-services4-data>=0.0.0
Requires-Dist: pip-services4-http>=0.0.0
Requires-Dist: pip-services4-mongodb>=0.0.0
Requires-Dist: pip-services4-persistence>=0.0.0
Requires-Dist: pip-services4-prometheus>=0.0.0
Requires-Dist: pip-services4-rpc>=0.0.0
Requires-Dist: pip-services4-swagger>=0.0.0
Dynamic: author
Dynamic: author-email
Dynamic: classifier
Dynamic: description
Dynamic: description-content-type
Dynamic: home-page
Dynamic: license
Dynamic: license-file
Dynamic: platform
Dynamic: requires-dist
Dynamic: summary
